Workbook
Name \a: #REF!
Name \a: #REF!
Name \a: #REF!
Name \b: #REF!
Name \b: #REF!
Name \b: #REF!
Name \c: #REF!
Name \c: #REF!
Name \c: #REF!
Name \d: #REF!
Name \e: #REF!
Name \f: #REF!
Name \g: #REF!
Name \h: #REF!
Name \j: #REF!
Name \k: #REF!
Name \l: #REF!
Name \m: #REF!
Name \n: #REF!
Name \p: #REF!
Name \q: #REF!
Name \r: #REF!
Name \s: #REF!
Name \t: #REF!
Name \u: #REF!
Name \v: #REF!
Name \w: #REF!
Name \x: #REF!
Name \y: #REF!
Name \z: #REF!
Name _._IMPUESTOS_SOBRE_COMBUSTIBLES_Y_GAS_NATURAL: [1]C!$B$27:$N$27
Name _._IMPUESTOS_SOBRE_ENERGIA_ELECTRICA: [1]C!$B$28:$N$28
Name _F: #REF!
Name _R: #REF!
Name A: #REF!
Name B: #REF!
Name Base_datos_IM: #REF!
Name BORRAR: #REF!
Name C_: #REF!
Name cantidad_prestada: '[2]IPV-BAPRO'!#REF!
Name Comisiones: #REF!
Name COPA: #N/A
Name COPARTICIPACION_FEDERAL__LEY_N__23548: [1]C!$B$13:$N$13
Name Criterios_IM: #REF!
Name E: #REF!
Name EXCEDENTE_DEL_10__SEGUN_EL_TOPE_ASIGNADO_A__BUENOS_AIRES__LEY_N__23621: [1]C!$B$18:$N$18
Name Extracción_IM: #REF!
Name Fecha_primer_pago: '[2]IPV-BAPRO'!#REF!
Name FONDO_COMPENSADOR_DE_DESEQUILIBRIOS_FISCALES_PROVINCIALES: [1]C!$B$15:$N$15
Name FONDO_EDUCATIVO__LEY_N__23906_ART._3_Y_4: [1]C!$B$16:$N$16
Name FONDO_ESPECIAL_DE_DESARROLLO_ELECTRICO_DEL_INTERIOR__LEYES_NROS._23966_ART._19_Y_24065: [1]C!$B$26:$N$26
Name FONDO_NACIONAL_DE_LA_VIVIENDA__LEY_N__23966_ART._18: [1]C!$B$25:$N$25
Name G: #REF!
Name H: #REF!
Name I: #REF!
Name IMPRIMIR: #REF!
Name J: #REF!
Name K: #REF!
Name L_: #N/A
Name M: #REF!

Sheet IIBB
N1: Última actualización | O1: 46297
B2: IMPUESTOS SOBRE LOS INGRESOS BRUTOS
B3: 2026
B4: en millones de pesos
B6: Jurisdicción | C6: Enero | D6: Febrero | E6: Marzo | F6: Abril | G6: Mayo | H6: Junio | I6: Julio | J6: Agosto | K6: Septiembre | L6: Octubre | M6: Noviembre | N6: Diciembre | O6: Total
B8: C.A.B.A. | C8: 759579.1 | D8: 711180.3 | E8: 644673.9 | F8: 714719.7 | G8: 750198.5 | H8: 737506.4 | I8: 783413.9 | J8: 807806.2 | K8: 0 | L8: 0 | M8: 0 | N8: 0 | O8: =SUM(C8:N8) -> 5909078
B9: Buenos Aires | C9: 1086193.5 | D9: 961709.43 | E9: 944164.54 | F9: 1084984.7 | G9: 1060147.3 | H9: 1156260.9 | I9: 1197577.6 | J9: 0 | K9: 0 | L9: 0 | M9: 0 | N9: 0 | O9: =SUM(C9:N9) -> 7491038
B10: Catamarca | C10: 21870.152 | D10: 18769 | E10: 18127.227 | F10: 20732.331 | G10: 20529.255 | H10: 21657.433 | I10: 23144.821 | J10: 23293.551 | K10: 20849.844 | L10: 0 | M10: 0 | N10: 0 | O10: =SUM(C10:N10) -> 188973.61
B11: Córdoba | C11: 277942.44 | D11: 242946.5 | E11: 245101.44 | F11: 260877.64 | G11: 272287.85 | H11: 271632.29 | I11: 275249.34 | J11: 281578.51 | K11: 0 | L11: 0 | M11: 0 | N11: 0 | O11: =SUM(C11:N11) -> 2127616
B12: Corrientes | C12: 31388.156 | D12: 30211.81 | E12: 28772.438 | F12: 32059.957 | G12: 32161.158 | H12: 32702.148 | I12: 33839.744 | J12: 0 | K12: 0 | L12: 0 | M12: 0 | N12: 0 | O12: =SUM(C12:N12) -> 221135.41
B13: Chaco | C13: 33654.962 | D13: 31721.62 | E13: 28963.61 | F13: 30813.302 | G13: 31627.758 | H13: 33417.513 | I13: 36452.558 | J13: 37011.91 | K13: 0 | L13: 0 | M13: 0 | N13: 0 | O13: =SUM(C13:N13) -> 263663.23
B14: Chubut (*) | C14: 49522.085 | D14: 45753.886 | E14: 41764.975 | F14: 46964.932 | G14: 48912.075 | H14: 48360.678 | I14: 59118.946 | J14: 53052.972 | K14: 53969 | L14: 0 | M14: 0 | N14: 0 | O14: =SUM(C14:N14) -> 447419.55
B15: Entre Ríos | C15: 71086.672 | D15: 64033.056 | E15: 61766.403 | F15: 67785.222 | G15: 67360.574 | H15: 71000.46 | I15: 72164.557 | J15: 74265.59 | K15: 0 | L15: 0 | M15: 0 | N15: 0 | O15: =SUM(C15:N15) -> 549462.53
B16: Formosa | C16: 13853.671 | D16: 13091.204 | E16: 12710.473 | F16: 13819.897 | G16: 16554.107 | H16: 16142.334 | I16: 16466.41 | J16: 17367.111 | K16: 17068.619 | L16: 0 | M16: 0 | N16: 0 | O16: =SUM(C16:N16) -> 137073.83
B17: Jujuy | C17: 25337.645 | D17: 23522.391 | E17: 23692.42 | F17: 24783.803 | G17: 26407.681 | H17: 26470.799 | I17: 27597.065 | J17: 27979.338 | K17: 0 | L17: 0 | M17: 0 | N17: 0 | O17: =SUM(C17:N17) -> 205791.14
B18: La Pampa | C18: 35892.893 | D18: 25307.5 | E18: 34479.599 | F18: 29660.028 | G18: 32620.483 | H18: 41994.21 | I18: 39666.187 | J18: 0 | K18: 0 | L18: 0 | M18: 0 | N18: 0 | O18: =SUM(C18:N18) -> 239620.9
B19: La Rioja | C19: 11905.858 | D19: 10431.229 | E19: 10141.297 | F19: 12154.995 | G19: 11506.151 | H19: 12236.696 | I19: 12720.151 | J19: 11573.442 | K19: 0 | L19: 0 | M19: 0 | N19: 0 | O19: =SUM(C19:N19) -> 92669.82
... B31: Tierra del Fuego | C31: 15966.197 | D31: 16443.894 | E31: 14093.73 | F31: 16785.535 | G31: 14835.389 | H31: 15456.1 | I31: 15948.205 | J31: 17843.664 | K31: 0 | L31: 0 | M31: 0 | N31: 0 | O31: =SUM(C31:N31) -> 127372.71
B32: Total | C32: =SUM(C8:C31) -> 3370791.1 | D32: =SUM(D8:D31) -> 3067849.7 | E32: =SUM(E8:E31) -> 2929071.3 | F32: =SUM(F8:F31) -> 3284092.6 | G32: =SUM(G8:G31) -> 3346953.2 | H32: =SUM(H8:H31) -> 3471232.4 | I32: =SUM(I8:I31) -> 3555893 | J32: =SUM(J8:J31) -> 2119549.1 | ... O32: =SUM(O8:O31) -> 25262518
B33: Notas:
B34: Fuente: Direcciones de Rentas o Administraciones Tributarias Provinciales. Para más detalle ver hoja "Fuente-Metodología".
B35: (*) sólo incluye la derivada del Convenio Multilateral y contribuyentes directos fuera de ejido municipal. La originada por contribuyentes directos dentro del ejido municipal se encuentra delegada a los gobiernos municipales
B36: SUBSECRETARÍA DE COORDINACIÓN FISCAL PROVINCIAL

Sheet INMOBILIARIO
N1: =+IIBB!N1 -> Última actualización | O1: =+IIBB!O1 -> 46297
B2: IMPUESTO INMOBILIARIO
B3: =+IIBB!B3 -> 2026
B4: en millones de pesos
B6: Jurisdicción | C6: Enero | D6: Febrero | E6: Marzo | F6: Abril | G6: Mayo | H6: Junio | I6: Julio | J6: Agosto | K6: Septiembre | L6: Octubre | M6: Noviembre | N6: Diciembre | O6: Total
B8: C.A.B.A. | C8: 184080.8 | D8: 67615.7 | E8: 67899.1 | F8: 70713.5 | G8: 78150.3 | H8: 76143.3 | I8: 80207.5 | J8: 78469.1 | K8: 0 | L8: 0 | M8: 0 | N8: 0 | O8: =SUM(C8:N8) -> 703279.3
B9: Buenos Aires | C9: 26695.322 | D9: 177086.64 | E9: 129891.38 | F9: 96687.897 | G9: 30836.735 | H9: 150011.97 | I9: 31286.51 | J9: 0 | K9: 0 | L9: 0 | M9: 0 | N9: 0 | O9: =SUM(C9:N9) -> 642496.46
B10: Catamarca | C10: 272.52249 | D10: 700.51361 | E10: 1962.2393 | F10: 1483.1485 | G10: 867.19721 | H10: 657.73306 | I10: 1158.0564 | J10: 491.06707 | K10: 292.03405 | L10: 0 | M10: 0 | N10: 0 | O10: =SUM(C10:N10) -> 7884.5117
B11: Córdoba | C11: 45075.524 | D11: 85744.067 | E11: 61322.929 | F11: 56237.193 | G11: 91294.381 | H11: 44508.858 | I11: 29123.032 | J11: 27650.898 | K11: 0 | L11: 0 | M11: 0 | N11: 0 | O11: =SUM(C11:N11) -> 440956.88
B12: Corrientes | C12: 295.86018 | D12: 310.06835 | E12: 718.13711 | F12: 5275.9159 | G12: 525.78508 | H12: 1526.8833 | I12: 501.2105 | J12: 0 | K12: 0 | L12: 0 | M12: 0 | N12: 0 | O12: =SUM(C12:N12) -> 9153.8604
B13: Chaco | C13: 42.127874 | D13: 109.4813 | E13: 155.71712 | F13: 237.63898 | G13: 257.83436 | H13: 217.5335 | I13: 78.453227 | J13: 35.931434 | K13: 0 | L13: 0 | M13: 0 | N13: 0 | O13: =SUM(C13:N13) -> 1134.7178
B14: Chubut | C14: 30.513753 | D14: 21.953542 | E14: 27.938499 | F14: 47.358093 | G14: 127.85455 | H14: 120.65746 | I14: 59.592228 | J14: 38.95596 | K14: 43 | L14: 0 | M14: 0 | N14: 0 | O14: =SUM(C14:N14) -> 517.82408
B15: Entre Ríos | C15: 2777.234 | D15: 21947.15 | E15: 6351.9416 | F15: 11384.358 | G15: 29765.72 | H15: 12586.459 | I15: 13952.935 | J15: 12643.237 | K15: 0 | L15: 0 | M15: 0 | N15: 0 | O15: =SUM(C15:N15) -> 111409.03
B16: Formosa | C16: 53.696131 | D16: 51.507627 | E16: 106.65196 | F16: 90.597546 | G16: 157.41854 | H16: 166.92978 | I16: 154.14612 | J16: 117.9439 | K16: 168.86001 | L16: 0 | M16: 0 | N16: 0 | O16: =SUM(C16:N16) -> 1067.7516
B17: Jujuy | C17: 1444.9843 | D17: 2770.0879 | E17: 2784.6449 | F17: 809.5562 | G17: 466.65216 | H17: 585.15436 | I17: 689.96657 | J17: 734.69903 | K17: 0 | L17: 0 | M17: 0 | N17: 0 | O17: =SUM(C17:N17) -> 10285.745
B18: La Pampa | C18: 603.31671 | D18: 440.4323 | E18: 1489.8806 | F18: 7765.8285 | G18: 4018.6922 | H18: 4455.1754 | I18: 4948.1668 | J18: 0 | K18: 0 | L18: 0 | M18: 0 | N18: 0 | O18: =SUM(C18:N18) -> 23721.492
B19: La Rioja | C19: 177.77757 | D19: 331.47543 | E19: 1204.5789 | F19: 506.49487 | G19: 293.1149 | H19: 270.88437 | I19: 229.44346 | J19: 258.17669 | K19: 0 | L19: 0 | M19: 0 | N19: 0 | O19: =SUM(C19:N19) -> 3271.9462
... B31: Tierra del Fuego | C31: 1.1753365 | D31: 0.13771082 | E31: 0.23700027 | F31: 0.28018156 | G31: 0.17253475 | H31: 0.31500399 | I31: 0 | J31: 2.4975732 | K31: 0 | L31: 0 | M31: 0 | N31: 0 | O31: =SUM(C31:N31) -> 4.8153411
B32: Total | C32: =SUM(C8:C31) -> 299365.7 | D32: =SUM(D8:D31) -> 485570.91 | E32: =SUM(E8:E31) -> 314412.46 | F32: =SUM(F8:F31) -> 283350.5 | G32: =SUM(G8:G31) -> 260458.39 | H32: =SUM(H8:H31) -> 325317.43 | I32: =SUM(I8:I31) -> 192129.45 | J32: =SUM(J8:J31) -> 152616.41 | ... O32: =SUM(O8:O31) -> 2316551.9
B33: Nota:
B34: Fuente: Direcciones de Rentas o Administraciones Tributarias Provinciales. Para más detalle ver hoja "Fuente-Metodología".
B36: SUBSECRETARÍA DE COORDINACIÓN FISCAL PROVINCIAL

Sheet SELLOS
N1: =+IIBB!N1 -> Última actualización | O1: =+IIBB!O1 -> 46297
B2: IMPUESTOS A LOS SELLOS
B3: =+IIBB!B3 -> 2026
B4: en millones de pesos
B6: Jurisdicción | C6: Enero | D6: Febrero | E6: Marzo | F6: Abril | G6: Mayo | H6: Junio | I6: Julio | J6: Agosto | K6: Septiembre | L6: Octubre | M6: Noviembre | N6: Diciembre | O6: Total
B8: C.A.B.A. | C8: 92341 | D8: 72461.5 | E8: 65069.4 | F8: 75230.9 | G8: 76067.6 | H8: 74624.5 | I8: 78671.9 | J8: 81304.1 | K8: 0 | L8: 0 | M8: 0 | N8: 0 | O8: =SUM(C8:N8) -> 615770.9
B9: Buenos Aires | C9: 142812.81 | D9: 126193.69 | E9: 131929.68 | F9: 137090.09 | G9: 141157.44 | H9: 133786.04 | I9: 138562.6 | J9: 0 | K9: 0 | L9: 0 | M9: 0 | N9: 0 | O9: =SUM(C9:N9) -> 951532.36
B10: Catamarca | C10: 553.99611 | D10: 544.05201 | E10: 507.39832 | F10: 592.4639 | G10: 727.77062 | H10: 669.28858 | I10: 633.3152 | J10: 996.33348 | K10: 540.51528 | L10: 0 | M10: 0 | N10: 0 | O10: =SUM(C10:N10) -> 5765.1335
B11: Córdoba | C11: 37032.356 | D11: 28749.032 | E11: 36500.947 | F11: 37133.048 | G11: 35946.673 | H11: 35887.831 | I11: 39324.687 | J11: 38401.059 | K11: 0 | L11: 0 | M11: 0 | N11: 0 | O11: =SUM(C11:N11) -> 288975.63
B12: Corrientes | C12: 4915.4024 | D12: 4318.3559 | E12: 4713.0984 | F12: 5472.3684 | G12: 5230.0258 | H12: 5774.1254 | I12: 4995.8224 | J12: 0 | K12: 0 | L12: 0 | M12: 0 | N12: 0 | O12: =SUM(C12:N12) -> 35419.199
B13: Chaco | C13: 5943.7805 | D13: 5335.2329 | E13: 5405.1641 | F13: 5595.6245 | G13: 5438.5773 | H13: 5532.3618 | I13: 5987.1096 | J13: 6053.215 | K13: 0 | L13: 0 | M13: 0 | N13: 0 | O13: =SUM(C13:N13) -> 45291.066
B14: Chubut | C14: 17088.205 | D14: 7999.1441 | E14: 17134.05 | F14: 10640.711 | G14: 8178.8478 | H14: 8711.0171 | I14: 8040.3201 | J14: 9238.2053 | K14: 8691 | L14: 0 | M14: 0 | N14: 0 | O14: =SUM(C14:N14) -> 95721.5
B15: Entre Ríos | C15: 7977.8713 | D15: 7878.7169 | E15: 7723.9785 | F15: 8470.7446 | G15: 8489.0194 | H15: 8977.614 | I15: 9105.5016 | J15: 10145.34 | K15: 0 | L15: 0 | M15: 0 | N15: 0 | O15: =SUM(C15:N15) -> 68768.786
B16: Formosa | C16: 1403.0896 | D16: 1740.0076 | E16: 1783.3642 | F16: 2135.0971 | G16: 1629.6164 | H16: 1781.8046 | I16: 1700.6482 | J16: 2331.3206 | K16: 2388.5606 | L16: 0 | M16: 0 | N16: 0 | O16: =SUM(C16:N16) -> 16893.509
B17: Jujuy | C17: 3251.2271 | D17: 3386.0453 | E17: 2791.7643 | F17: 3144.5248 | G17: 2945.8765 | H17: 3149.1529 | I17: 3185.9768 | J17: 3551.0697 | K17: 0 | L17: 0 | M17: 0 | N17: 0 | O17: =SUM(C17:N17) -> 25405.637
B18: La Pampa | C18: 3580.9758 | D18: 1230.1491 | E18: 4872.3583 | F18: 3827.6783 | G18: 4262.9151 | H18: 3604.4977 | I18: 4862.567 | J18: 0 | K18: 0 | L18: 0 | M18: 0 | N18: 0 | O18: =SUM(C18:N18) -> 26241.141
B19: La Rioja | C19: 1771.6987 | D19: 1727.1183 | E19: 1828.8499 | F19: 1844.3229 | G19: 2124.4087 | H19: 2332.0519 | I19: 1913.6696 | J19: 2068.439 | K19: 0 | L19: 0 | M19: 0 | N19: 0 | O19: =SUM(C19:N19) -> 15610.559
... B31: Tierra del Fuego | C31: 1996.8373 | D31: 2070.7691 | E31: 1857.5493 | F31: 2012.4579 | G31: 2163.8597 | H31: 1974.1529 | I31: 2000.8742 | J31: 2470.7704 | K31: 0 | L31: 0 | M31: 0 | N31: 0 | O31: =SUM(C31:N31) -> 16547.271
B32: Total | C32: =SUM(C8:C31) -> 412523.8 | D32: =SUM(D8:D31) -> 351335.7 | E32: =SUM(E8:E31) -> 364105.34 | F32: =SUM(F8:F31) -> 379968.19 | G32: =SUM(G8:G31) -> 385225.55 | H32: =SUM(H8:H31) -> 376510.24 | I32: =SUM(I8:I31) -> 395993.31 | J32: =SUM(J8:J31) -> 234988.16 | ... O32: =SUM(O8:O31) -> 2915503.9
B33: Nota:
B34: Fuente: Direcciones de Rentas o Administraciones Tributarias Provinciales. Para más detalle ver hoja "Fuente-Metodología".
B36: SUBSECRETARÍA DE COORDINACIÓN FISCAL PROVINCIAL

Sheet AUTOMOTORES
N1: =+IIBB!N1 -> Última actualización | O1: =+IIBB!O1 -> 46297
B2: IMPUESTOS AUTOMOTOR
B3: =+IIBB!B3 -> 2026
B4: en millones de pesos
B6: Jurisdicción | C6: Enero | D6: Febrero | E6: Marzo | F6: Abril | G6: Mayo | H6: Junio | I6: Julio | J6: Agosto | K6: Septiembre | L6: Octubre | M6: Noviembre | N6: Diciembre | O6: Total
B8: C.A.B.A. | C8: 22764.4 | D8: 87703.1 | E8: 35478.9 | F8: 70253.2 | G8: 22555.3 | H8: 72261.9 | I8: 23775.7 | J8: 71069.7 | K8: 0 | L8: 0 | M8: 0 | N8: 0 | O8: =SUM(C8:N8) -> 405862.2
B9: Buenos Aires | C9: 27384.15 | D9: 18634.389 | E9: 120929.42 | F9: 66791.683 | G9: 62661.063 | H9: 68342.617 | I9: 69623.155 | J9: 0 | K9: 0 | L9: 0 | M9: 0 | N9: 0 | O9: =SUM(C9:N9) -> 434366.48
B10: Catamarca | C10: 625.53176 | D10: 938.17277 | E10: 2007.5206 | F10: 1904.2512 | G10: 1276.8004 | H10: 877.43017 | I10: 1344.67 | J10: 806.23777 | K10: 357.16085 | L10: 0 | M10: 0 | N10: 0 | O10: =SUM(C10:N10) -> 10137.775
B11: Córdoba | C11: 13494.367 | D11: 19007.17 | E11: 26153.404 | F11: 19064.584 | G11: 9352.3091 | H11: 9548.4752 | I11: 9738.4618 | J11: 9304.1713 | K11: 0 | L11: 0 | M11: 0 | N11: 0 | O11: =SUM(C11:N11) -> 115662.94
B12: Corrientes | C12: 0 | D12: 0 | E12: 0 | F12: 0 | G12: 0 | H12: 0 | I12: 0 | J12: 0 | K12: 0 | L12: 0 | M12: 0 | N12: 0 | O12: =SUM(C12:N12) -> 0
B13: Chaco | C13: 0 | D13: 0 | E13: 0 | F13: 0 | G13: 0 | H13: 0 | I13: 0 | J13: 0 | K13: 0 | L13: 0 | M13: 0 | N13: 0 | O13: =SUM(C13:N13) -> 0
B14: Chubut | C14: 0 | D14: 0 | E14: 0 | F14: 0 | G14: 0 | H14: 0 | I14: 0 | J14: 0 | K14: 0 | L14: 0 | M14: 0 | N14: 0 | O14: =SUM(C14:N14) -> 0
B15: Entre Ríos | C15: 2998.2586 | D15: 2075.4132 | E15: 6963.6916 | F15: 30426.658 | G15: 17627.228 | H15: 5160.1875 | I15: 20107.158 | J15: 4815.5487 | K15: 0 | L15: 0 | M15: 0 | N15: 0 | O15: =SUM(C15:N15) -> 90174.144
B16: Formosa | C16: 0 | D16: 0 | E16: 0 | F16: 0 | G16: 0 | H16: 0 | I16: 0 | J16: 0 | K16: 0 | L16: 0 | M16: 0 | N16: 0 | O16: =SUM(C16:N16) -> 0
B17: Jujuy | C17: 0 | D17: 0 | E17: 0 | F17: 0 | G17: 0 | H17: 0 | I17: 0 | J17: 0 | K17: 0 | L17: 0 | M17: 0 | N17: 0 | O17: =SUM(C17:N17) -> 0
B18: La Pampa | C18: 2514.5517 | D18: 4482.8415 | E18: 3029.0529 | F18: 4215.9566 | G18: 2439.4792 | H18: 4416.1244 | I18: 2202.5879 | J18: 0 | K18: 0 | L18: 0 | M18: 0 | N18: 0 | O18: =SUM(C18:N18) -> 23300.594
B19: La Rioja | C19: 465.70864 | D19: 561.50006 | E19: 814.62135 | F19: 1641.4311 | G19: 997.96493 | H19: 826.47228 | I19: 852.04307 | J19: 875.5414 | K19: 0 | L19: 0 | M19: 0 | N19: 0 | O19: =SUM(C19:N19) -> 7035.2828
... B31: Tierra del Fuego | C31: 0 | D31: 0 | E31: 0 | F31: 0 | G31: 0 | H31: 0 | I31: 0 | J31: 0 | K31: 0 | L31: 0 | M31: 0 | N31: 0 | O31: =SUM(C31:N31) -> 0
B32: Total | C32: =SUM(C8:C31) -> 93964.173 | D32: =SUM(D8:D31) -> 174327.19 | E32: =SUM(E8:E31) -> 246454.46 | F32: =SUM(F8:F31) -> 221644.07 | G32: =SUM(G8:G31) -> 145016.01 | H32: =SUM(H8:H31) -> 186017.07 | I32: =SUM(I8:I31) -> 157172.93 | J32: =SUM(J8:J31) -> 111384.47 | ... O32: =SUM(O8:O31) -> 1337547.9
B33: Nota:
B34: Fuente: Direcciones de Rentas o Administraciones Tributarias Provinciales. Para más detalle ver hoja "Fuente-Metodología".
B36: SUBSECRETARÍA DE COORDINACIÓN FISCAL PROVINCIAL

Sheet OTROS
N1: =+IIBB!N1 -> Última actualización | O1: =+IIBB!O1 -> 46297
B2: OTROS IMPUESTOS
B3: =+IIBB!B3 -> 2026
B4: en millones de pesos
B6: Jurisdicción | C6: Enero | D6: Febrero | E6: Marzo | F6: Abril | G6: Mayo | H6: Junio | I6: Julio | J6: Agosto | K6: Septiembre | L6: Octubre | M6: Noviembre | N6: Diciembre | O6: Total
B8: C.A.B.A. | C8: 66177.6 | D8: 34761.1 | E8: 21763.4 | F8: 22766.1 | G8: 17718.4 | H8: 13369.2 | I8: 14376.6 | J8: 11516.8 | K8: 0 | L8: 0 | M8: 0 | N8: 0 | O8: =SUM(C8:N8) -> 202449.2
B9: Buenos Aires | C9: 31266.522 | D9: 36016.228 | E9: 39482.381 | F9: 39679.532 | G9: 46836.261 | H9: 53690.279 | I9: 50963.896 | J9: 0 | K9: 0 | L9: 0 | M9: 0 | N9: 0 | O9: =SUM(C9:N9) -> 297935.1
B10: Catamarca | C10: 10.743643 | D10: 21.433944 | E10: 62.819596 | F10: 33.303708 | G10: 38.104526 | H10: 50.697676 | I10: 36.552014 | J10: 76.149426 | K10: 49.569578 | L10: 0 | M10: 0 | N10: 0 | O10: =SUM(C10:N10) -> 379.37411
B11: Córdoba | C11: 0 | D11: 0 | E11: 0 | F11: 0 | G11: 0 | H11: 0 | I11: 0 | J11: 0 | K11: 0 | L11: 0 | M11: 0 | N11: 0 | O11: =SUM(C11:N11) -> 0
B12: Corrientes | C12: 76.439363 | D12: 47.317616 | E12: 79.213275 | F12: 73.033898 | G12: 64.418509 | H12: 68.546042 | I12: 71.524767 | J12: 0 | K12: 0 | L12: 0 | M12: 0 | N12: 0 | O12: =SUM(C12:N12) -> 480.49347
B13: Chaco | C13: 8561.4033 | D13: 6263.5034 | E13: 5981.8606 | F13: 6277.3838 | G13: 6384.8884 | H13: 6545.4909 | I13: 9024.558 | J13: 7794.7612 | K13: 0 | L13: 0 | M13: 0 | N13: 0 | O13: =SUM(C13:N13) -> 56833.85
B14: Chubut | C14: 965.01557 | D14: 1539.0933 | E14: 833.02316 | F14: 376.71737 | G14: 113.85371 | H14: 348.62374 | I14: 126.76968 | J14: 118.37397 | K14: 95 | L14: 0 | M14: 0 | N14: 0 | O14: =SUM(C14:N14) -> 4516.4705
B15: Entre Ríos | C15: 2407.6587 | D15: 1922.4301 | E15: 2385.3696 | F15: 2499.0714 | G15: 2471.3703 | H15: 2692.0324 | I15: 3271.0862 | J15: 2782.7092 | K15: 0 | L15: 0 | M15: 0 | N15: 0 | O15: =SUM(C15:N15) -> 20431.728
B16: Formosa | C16: 26.780124 | D16: 32.620815 | E16: 24.589942 | F16: 24.426393 | G16: 35.32275 | H16: 75.128536 | I16: 79.783358 | J16: 79.013336 | K16: 44.279351 | L16: 0 | M16: 0 | N16: 0 | O16: =SUM(C16:N16) -> 421.9446
B17: Jujuy | C17: 0 | D17: 0 | E17: 0 | F17: 0 | G17: 0 | H17: 0 | I17: 0 | J17: 0 | K17: 0 | L17: 0 | M17: 0 | N17: 0 | O17: =SUM(C17:N17) -> 0
B18: La Pampa | C18: 30.122652 | D18: 22.839392 | E18: 108.49174 | F18: 410.29354 | G18: 354.78623 | H18: 312.97359 | I18: 303.72665 | J18: 0 | K18: 0 | L18: 0 | M18: 0 | N18: 0 | O18: =SUM(C18:N18) -> 1543.2338
B19: La Rioja | C19: 0 | D19: 0 | E19: 0 | F19: 0 | G19: 0 | H19: 0 | I19: 0 | J19: 0 | K19: 0 | L19: 0 | M19: 0 | N19: 0 | O19: =SUM(C19:N19) -> 0
... B31: Tierra del Fuego | C31: 12658.171 | D31: 11296.943 | E31: 11404.535 | F31: 13850.751 | G31: 11881.3 | H31: 11865.639 | I31: 13476.534 | J31: 13879.305 | K31: 0 | L31: 0 | M31: 0 | N31: 0 | O31: =SUM(C31:N31) -> 100313.18
B32: Total | C32: =SUM(C8:C31) -> 134610.51 | D32: =SUM(D8:D31) -> 100634.19 | E32: =SUM(E8:E31) -> 91169.792 | F32: =SUM(F8:F31) -> 95826.879 | G32: =SUM(G8:G31) -> 94615.993 | H32: =SUM(H8:H31) -> 99227.718 | I32: =SUM(I8:I31) -> 104232.05 | J32: =SUM(J8:J31) -> 45827.777 | ... O32: =SUM(O8:O31) -> 766538.44
B33: Nota:
B34: Fuente: Direcciones de Rentas o Administraciones Tributarias Provinciales. Para más detalle ver hoja "Fuente-Metodología".
B36: SUBSECRETARÍA DE COORDINACIÓN FISCAL PROVINCIAL

Sheet TOTAL
N1: =+IIBB!N1 -> Última actualización | O1: =+IIBB!O1 -> 46297
B2: RECURSOS TRIBUTARIOS PROVINCIALES
B3: =+IIBB!B3 -> 2026
B4: en millones de pesos
B6: Jurisdicción | C6: Enero | D6: Febrero | E6: Marzo | F6: Abril | G6: Mayo | H6: Junio | I6: Julio | J6: Agosto | K6: Septiembre | L6: Octubre | M6: Noviembre | N6: Diciembre | O6: Total
B8: C.A.B.A. | C8: =+SUM(IIBB:OTROS!C8) -> 1124942.9 | D8: =+SUM(IIBB:OTROS!D8) -> 973721.7 | E8: =+SUM(IIBB:OTROS!E8) -> 834884.7 | F8: =+SUM(IIBB:OTROS!F8) -> 953683.4 | G8: =+SUM(IIBB:OTROS!G8) -> 944690.1 | H8: =+SUM(IIBB:OTROS!H8) -> 973905.3 | I8: =+SUM(IIBB:OTROS!I8) -> 980445.6 | J8: =+SUM(IIBB:OTROS!J8) -> 1050165.9 | ... N8: =+SUM(IIBB:OTROS!N8) -> 0 | O8: =SUM(C8:N8) -> 7836439.6
B9: Buenos Aires | C9: =+SUM(IIBB:OTROS!C9) -> 1314352.3 | D9: =+SUM(IIBB:OTROS!D9) -> 1319640.4 | E9: =+SUM(IIBB:OTROS!E9) -> 1366397.4 | F9: =+SUM(IIBB:OTROS!F9) -> 1425233.9 | G9: =+SUM(IIBB:OTROS!G9) -> 1341638.8 | H9: =+SUM(IIBB:OTROS!H9) -> 1562091.8 | I9: =+SUM(IIBB:OTROS!I9) -> 1488013.8 | J9: =+SUM(IIBB:OTROS!J9) -> 0 | ... N9: =+SUM(IIBB:OTROS!N9) -> 0 | O9: =SUM(C9:N9) -> 9817368.4
B10: Catamarca | C10: =+SUM(IIBB:OTROS!C10) -> 23332.946 | D10: =+SUM(IIBB:OTROS!D10) -> 20973.172 | E10: =+SUM(IIBB:OTROS!E10) -> 22667.205 | F10: =+SUM(IIBB:OTROS!F10) -> 24745.498 | G10: =+SUM(IIBB:OTROS!G10) -> 23439.128 | H10: =+SUM(IIBB:OTROS!H10) -> 23912.582 | I10: =+SUM(IIBB:OTROS!I10) -> 26317.415 | J10: =+SUM(IIBB:OTROS!J10) -> 25663.339 | ... N10: =+SUM(IIBB:OTROS!N10) -> 0 | O10: =SUM(C10:N10) -> 213140.41
B11: Córdoba | C11: =+SUM(IIBB:OTROS!C11) -> 373544.68 | D11: =+SUM(IIBB:OTROS!D11) -> 376446.77 | E11: =+SUM(IIBB:OTROS!E11) -> 369078.72 | F11: =+SUM(IIBB:OTROS!F11) -> 373312.46 | G11: =+SUM(IIBB:OTROS!G11) -> 408881.22 | H11: =+SUM(IIBB:OTROS!H11) -> 361577.45 | I11: =+SUM(IIBB:OTROS!I11) -> 353435.52 | J11: =+SUM(IIBB:OTROS!J11) -> 356934.64 | ... N11: =+SUM(IIBB:OTROS!N11) -> 0 | O11: =SUM(C11:N11) -> 2973211.5
B12: Corrientes | C12: =+SUM(IIBB:OTROS!C12) -> 36675.858 | D12: =+SUM(IIBB:OTROS!D12) -> 34887.552 | E12: =+SUM(IIBB:OTROS!E12) -> 34282.887 | F12: =+SUM(IIBB:OTROS!F12) -> 42881.275 | G12: =+SUM(IIBB:OTROS!G12) -> 37981.387 | H12: =+SUM(IIBB:OTROS!H12) -> 40071.703 | I12: =+SUM(IIBB:OTROS!I12) -> 39408.301 | J12: =+SUM(IIBB:OTROS!J12) -> 0 | ... N12: =+SUM(IIBB:OTROS!N12) -> 0 | O12: =SUM(C12:N12) -> 266188.96
B13: Chaco | C13: =+SUM(IIBB:OTROS!C13) -> 48202.274 | D13: =+SUM(IIBB:OTROS!D13) -> 43429.837 | E13: =+SUM(IIBB:OTROS!E13) -> 40506.351 | F13: =+SUM(IIBB:OTROS!F13) -> 42923.95 | G13: =+SUM(IIBB:OTROS!G13) -> 43709.058 | H13: =+SUM(IIBB:OTROS!H13) -> 45712.899 | I13: =+SUM(IIBB:OTROS!I13) -> 51542.679 | J13: =+SUM(IIBB:OTROS!J13) -> 50895.818 | ... N13: =+SUM(IIBB:OTROS!N13) -> 0 | O13: =SUM(C13:N13) -> 366922.87
B14: Chubut | C14: =+SUM(IIBB:OTROS!C14) -> 67605.819 | D14: =+SUM(IIBB:OTROS!D14) -> 55314.077 | E14: =+SUM(IIBB:OTROS!E14) -> 59759.986 | F14: =+SUM(IIBB:OTROS!F14) -> 58029.719 | G14: =+SUM(IIBB:OTROS!G14) -> 57332.632 | H14: =+SUM(IIBB:OTROS!H14) -> 57540.976 | I14: =+SUM(IIBB:OTROS!I14) -> 67345.628 | J14: =+SUM(IIBB:OTROS!J14) -> 62448.508 | ... N14: =+SUM(IIBB:OTROS!N14) -> 0 | O14: =SUM(C14:N14) -> 548175.35
B15: Entre Ríos | C15: =+SUM(IIBB:OTROS!C15) -> 87247.695 | D15: =+SUM(IIBB:OTROS!D15) -> 97856.766 | E15: =+SUM(IIBB:OTROS!E15) -> 85191.384 | F15: =+SUM(IIBB:OTROS!F15) -> 120566.05 | G15: =+SUM(IIBB:OTROS!G15) -> 125713.91 | H15: =+SUM(IIBB:OTROS!H15) -> 100416.75 | I15: =+SUM(IIBB:OTROS!I15) -> 118601.24 | J15: =+SUM(IIBB:OTROS!J15) -> 104652.42 | ... N15: =+SUM(IIBB:OTROS!N15) -> 0 | O15: =SUM(C15:N15) -> 840246.22
B16: Formosa | C16: =+SUM(IIBB:OTROS!C16) -> 15337.237 | D16: =+SUM(IIBB:OTROS!D16) -> 14915.34 | E16: =+SUM(IIBB:OTROS!E16) -> 14625.079 | F16: =+SUM(IIBB:OTROS!F16) -> 16070.019 | G16: =+SUM(IIBB:OTROS!G16) -> 18376.465 | H16: =+SUM(IIBB:OTROS!H16) -> 18166.197 | I16: =+SUM(IIBB:OTROS!I16) -> 18400.988 | J16: =+SUM(IIBB:OTROS!J16) -> 19895.389 | ... N16: =+SUM(IIBB:OTROS!N16) -> 0 | O16: =SUM(C16:N16) -> 155457.03
B17: Jujuy | C17: =+SUM(IIBB:OTROS!C17) -> 30033.856 | D17: =+SUM(IIBB:OTROS!D17) -> 29678.525 | E17: =+SUM(IIBB:OTROS!E17) -> 29268.829 | F17: =+SUM(IIBB:OTROS!F17) -> 28737.884 | G17: =+SUM(IIBB:OTROS!G17) -> 29820.21 | H17: =+SUM(IIBB:OTROS!H17) -> 30205.106 | I17: =+SUM(IIBB:OTROS!I17) -> 31473.009 | J17: =+SUM(IIBB:OTROS!J17) -> 32265.107 | ... N17: =+SUM(IIBB:OTROS!N17) -> 0 | O17: =SUM(C17:N17) -> 241482.53
B18: La Pampa | C18: =+SUM(IIBB:OTROS!C18) -> 42621.86 | D18: =+SUM(IIBB:OTROS!D18) -> 31483.763 | E18: =+SUM(IIBB:OTROS!E18) -> 43979.383 | F18: =+SUM(IIBB:OTROS!F18) -> 45879.785 | G18: =+SUM(IIBB:OTROS!G18) -> 43696.355 | H18: =+SUM(IIBB:OTROS!H18) -> 54782.982 | I18: =+SUM(IIBB:OTROS!I18) -> 51983.235 | J18: =+SUM(IIBB:OTROS!J18) -> 0 | ... N18: =+SUM(IIBB:OTROS!N18) -> 0 | O18: =SUM(C18:N18) -> 314427.36
B19: La Rioja | C19: =+SUM(IIBB:OTROS!C19) -> 14321.043 | D19: =+SUM(IIBB:OTROS!D19) -> 13051.323 | E19: =+SUM(IIBB:OTROS!E19) -> 13989.347 | F19: =+SUM(IIBB:OTROS!F19) -> 16147.244 | G19: =+SUM(IIBB:OTROS!G19) -> 14921.64 | H19: =+SUM(IIBB:OTROS!H19) -> 15666.104 | I19: =+SUM(IIBB:OTROS!I19) -> 15715.307 | J19: =+SUM(IIBB:OTROS!J19) -> 14775.599 | ... N19: =+SUM(IIBB:OTROS!N19) -> 0 | O19: =SUM(C19:N19) -> 118587.61
... B31: Tierra del Fuego | C31: =+SUM(IIBB:OTROS!C31) -> 30622.38 | D31: =+SUM(IIBB:OTROS!D31) -> 29811.744 | E31: =+SUM(IIBB:OTROS!E31) -> 27356.051 | F31: =+SUM(IIBB:OTROS!F31) -> 32649.024 | G31: =+SUM(IIBB:OTROS!G31) -> 28880.721 | H31: =+SUM(IIBB:OTROS!H31) -> 29296.207 | I31: =+SUM(IIBB:OTROS!I31) -> 31425.613 | J31: =+SUM(IIBB:OTROS!J31) -> 34196.237 | ... N31: =+SUM(IIBB:OTROS!N31) -> 0 | O31: =SUM(C31:N31) -> 244237.98
B32: Total | C32: =SUM(C8:C31) -> 4311255.3 | D32: =SUM(D8:D31) -> 4179717.6 | E32: =SUM(E8:E31) -> 3945213.4 | F32: =SUM(F8:F31) -> 4264882.3 | G32: =SUM(G8:G31) -> 4232269.2 | H32: =SUM(H8:H31) -> 4458304.8 | I32: =SUM(I8:I31) -> 4405420.8 | J32: =SUM(J8:J31) -> 2664366 | ... O32: =SUM(O8:O31) -> 32598660
B33: Nota:
B34: Fuente: Direcciones de Rentas o Administraciones Tributarias Provinciales. Para más detalle ver hoja "Fuente-Metodología".
B36: SUBSECRETARÍA DE COORDINACIÓN FISCAL PROVINCIAL

Sheet Fuente-Metodología
B1: CONSIDERACIONES METODOLÓGICAS
B2: La información de tributarios provinciales mensuales proviene de las Direcciones de Rentas o Administraciones Tributarias Provinciales. Consecuentemente, la Dirección Nacional de Asuntos Provinciales sólo la replica tal como es divulgada por dichos organismos sin realizar modificaciones ni cambios de ninguna naturaleza. Cabe aclarar que, por ejemplo, puede incluir recursos no tributarios cuya recaudación se encuentra bajo la órbita de los organismos recaudadores. La periodicidad de la publicación es mensual pero podría variar en función de la información disponible en las páginas web provinciales consultadas. Los montos podrían ser rectificados en función de la disponibilidad de nuevos datos. Adicionalmente, se recuerda que la distribución de potestades tributarias no es homogénea en todas las jurisdicciones por lo que deben tenerse en cuenta a la hora de confeccionar comparaciones. Los datos del presente informe corresponden exclusivamente a los ingresos de potestad provincial. Para consultar información municipal puede dirigirse a los sitios WEB oficiales de cada jurisdicción o: https://www.economia.gob.ar/dnap/municipios.html
B6: Jurisdicción | C6: Sitio Web
B8: CABA | C8: https://www.agip.gob.ar/informacion-de-utilidad/recaudacion/recaudacion
B9: Buenos Aires | C9: https://www.gba.gob.ar/economia/direccion_provincial_de_politica_tributaria/recaudacion_provincial
B10: Catamarca | C10: https://dgrentas.arcat.gob.ar/recaudacion.php
B11: Córdoba | C11: https://economiaygestionpublica.cba.gov.ar/publicacion/ingresos-tributarios/
B12: Corrientes | C12: Información remitida por la provincia
B13: Chaco | C13: https://atp.chaco.gob.ar/recaudacion
B14: Chubut | C14: Información remitida por la provincia. Para el mes de septiembre se tomó como fuente de información la página web de la Agencia de Recaudación de la Provincia: https://www.arech.gob.ar/institucional/estadisticas
B15: Entre Ríos | C15: https://portal.entrerios.gov.ar/haciendayfinanzas/analisisfiscal/ps/ingresospublicos/6792
B16: Formosa | C16: https://www.formosa.gob.ar/atp/recaudaciones
B17: Jujuy | C17: https://www.rentasjujuy.gob.ar/recaudacion/
B18: La Pampa | C18: Dirección General de Rentas de La Pampa. Datos publicados en el sitio de la Contaduría General de la provincia. https://contaduriageneral.lapampa.gob.ar/ejecucion-presupuestaria/ano-2026/informe-de-recursos-mensual
... B31: Tierra del Fuego | C31: https://www.aref.gob.ar/estadistica-tributaria/
B34: SUBSECRETARÍA DE COORDINACIÓN FISCAL PROVINCIAL

Sheet Potestades Tributarias
A1: POTESTADES TRIBUTARIAS DELEGADAS
A8: Jurisdicción | B8: Ingresos Brutos | D8: Inmobiliario | F8: Automotor | G8: Sellos
B9: Directos | C9: Conv. Mult. | D9: Urbano | E9: Rural
A10: Buenos Aires | B10: Provincial | C10: Provincial | D10: Provincial | E10: Provincial | F10: Provincial | G10: Provincial
A11: Catamarca | B11: Provincial | C11: Provincial | D11: Provincial | E11: Provincial | F11: Provincial | G11: Provincial
A12: Córdoba | B12: Provincial | C12: Provincial | D12: Provincial | E12: Provincial | F12: Municipal | G12: Provincial
A13: Corrientes | B13: Provincial | C13: Provincial | D13: Municipal | E13: Provincial | F13: Municipal | G13: Provincial
A14: Chaco | B14: Provincial | C14: Provincial | D14: Municipal | E14: Provincial | F14: Municipal | G14: Provincial
A15: Chubut | B15: Municipal (*) | C15: Provincial | D15: Municipal | E15: Municipal | F15: Municipal | G15: Provincial
A16: Entre Ríos | B16: Provincial | C16: Provincial | D16: Provincial | E16: Provincial | F16: Provincial | G16: Provincial
A17: Formosa | B17: Provincial | C17: Provincial | D17: Municipal | E17: Provincial | F17: Municipal | G17: Provincial
A18: Jujuy | B18: Provincial | C18: Provincial | D18: Provincial | E18: Provincial | F18: Municipal (**) | G18: Provincial
A19: La Pampa | B19: Provincial | C19: Provincial | D19: Provincial | E19: Provincial | F19: Provincial | G19: Provincial
A20: La Rioja | B20: Provincial | C20: Provincial | D20: Provincial | E20: Provincial | F20: Provincial | G20: Provincial
A21: Mendoza | B21: Provincial | C21: Provincial | D21: Provincial | E21: Provincial | F21: Provincial | G21: Provincial
... A32: Tierra del Fuego | B32: Provincial | C32: Provincial | D32: Municipal | E32: Provincial | F32: Municipal | G32: Provincial
A33: Fuente: Dirección Nacional de Asuntos Provinciales.
A35: Notas:
A36: (*) La recaudación del Impuesto sobre los Ingresos Brutos a nivel provincial incluye la derivada del Convenio Multilateral y contribuyentes directos fuera de ejido municipal, en razón que la originada por contribuyentes directos dentro del ejido municipal se encuentra delegada a los gobiernos municipales.
A37: (**) De acuerdo a la Constitución Provincial el impuesto es de potestad municipal, aunque en la práctica la estructura del impuesto la define la Provincia y la gestión del cobro esta descentralizada.
A39: SUBSECRETARÍA DE COORDINACIÓN FISCAL PROVINCIAL
